mtdaq/__init__.py
mtdaq/mtdaq.py
mtdaq-1.0.11.dist-info/METADATA
mtdaq-1.0.11.dist-info/WHEEL
mtdaq-1.0.11.dist-info/top_level.txt
mtdaq-1.0.11.dist-info/zip-safe
mtdaq-1.0.11.dist-info/RECORD
