Metadata-Version: 2.1
Name: mtdaq
Version: 1.0.11
Summary: MangoTree DAQ Device
Home-page: https://www.mangotree.cn/
Author: MangoTree
Author-email: support@mangotree.cn
License: MIT
